main.py
multiverse_rl-0.1.0.dist-info/METADATA
multiverse_rl-0.1.0.dist-info/WHEEL
multiverse_rl-0.1.0.dist-info/top_level.txt
multiverse_rl-0.1.0.dist-info/RECORD
