Metadata-Version: 2.4
Name: multiverse-rl
Version: 0.1.0
Summary: Multiverse
License: MIT
Requires-Python: >=3.12
